MANIFEST.in
setup.py
libpebble/LightBluePebble.py
libpebble/__init__.py
libpebble/p.py
libpebble/pebble.py
libpebble/stm32_crc.py
pebble_remote/__init__.py
pebble_remote/i18n.py
pebble_remote.egg-info/PKG-INFO
pebble_remote.egg-info/SOURCES.txt
pebble_remote.egg-info/dependency_links.txt
pebble_remote.egg-info/not-zip-safe
pebble_remote.egg-info/requires.txt
pebble_remote.egg-info/top_level.txt
pebble_remote/data/i18n/ca/LC_MESSAGES/pebble-remote.mo
pebble_remote/data/i18n/de/LC_MESSAGES/pebble-remote.mo
pebble_remote/data/i18n/es/LC_MESSAGES/pebble-remote.mo
pebble_remote/data/i18n/it/LC_MESSAGES/pebble-remote.mo
pebble_remote/data/i18n/sl/LC_MESSAGES/pebble-remote.mo
pebble_remote/data/i18n/tr/LC_MESSAGES/pebble-remote.mo
pebble_remote/data/man/pebble-remote.1.gz
pebble_remote/data/mimetype/pebble-remote
pebble_remote/data/mimetype/pebble-remote.desktop
pebble_remote/data/mimetype/pebble-remote.png
pebble_remote/data/scripts/exit_click.sh
pebble_remote/data/scripts/pebble-remote