Metadata-Version: 1.0
Name: pebble-remote
Version: 2.1
Summary: Remote control for LibreOffice Impress with Pebble
Home-page: https://github.com/LibreOffice/impress_remote/tree/master/pebble
Author: Gulsah KOSE
Author-email: gulsah.1004@gmail.com
License: MPLv2
Platform: UNKNOWN
